dschef/__init__.py
dschef/cli.py
dschef/dschef.py
dschef-0.1.0.dist-info/AUTHORS.rst
dschef-0.1.0.dist-info/LICENSE
dschef-0.1.0.dist-info/METADATA
dschef-0.1.0.dist-info/WHEEL
dschef-0.1.0.dist-info/entry_points.txt
dschef-0.1.0.dist-info/top_level.txt
dschef-0.1.0.dist-info/RECORD
