Metadata-Version: 2.1
Name: dschef
Version: 0.1.0
Summary: DataScience Chef - Receipes for ML
Home-page: https://github.com/sachin@crispai.com/dschef
Author: Sachin Naik
Author-email: sachin@crispai.com
License: BSD license
Keywords: dschef
Platform: UNKNOWN
Classifier: Development Status :: 2 - Pre-Alpha
Classifier: Intended Audience :: Developers
Classifier: License :: OSI Approved :: BSD License
Classifier: Natural Language :: English
Classifier: Programming Language :: Python :: 2
Classifier: Programming Language :: Python :: 2.7
Classifier: Programming Language :: Python :: 3
Classifier: Programming Language :: Python :: 3.5
Classifier: Programming Language :: Python :: 3.6
Classifier: Programming Language :: Python :: 3.7
Requires-Python: >=2.7, !=3.0.*, !=3.1.*, !=3.2.*, !=3.3.*, !=3.4.*
